mypackage/__init__.py
mypackage/decorators.py
mypackage/descriptors.py
mypackage/generators.py
mypackage/iterators.py
mypackage/main.py
LAB_11-0.1.0.dist-info/LICENSE
LAB_11-0.1.0.dist-info/METADATA
LAB_11-0.1.0.dist-info/WHEEL
LAB_11-0.1.0.dist-info/top_level.txt
LAB_11-0.1.0.dist-info/RECORD
