Metadata-Version: 2.1
Name: LAB_11
Version: 0.1.0
Summary: Краткое описание mypackage
Home-page: https://github.com/ваш_репозиторий
Author: VeroKulak
Author-email: nickkol31@gmail.com
Classifier: Programming Language :: Python :: 3
Classifier: License :: OSI Approved :: MIT License
Classifier: Operating System :: OS Independent
Requires-Python: >=3.6
License-File: LICENSE
